secure_settings/__init__.py
secure_settings/main.py
secure_settings/main.py.bak
secure_settings-1.0.3.dist-info/WHEEL
secure_settings-1.0.3.dist-info/METADATA
secure_settings-1.0.3.dist-info/RECORD
